INSTALL.rst
LICENSE
MANIFEST.in
README.rst
setup.py
bin/metquest.sh
metquest/__init__.py
metquest/construct_graph.py
metquest/execute_metquest.py
metquest/fetch_reactions.py
metquest/generate_partitions.py
metquest/get_reaction_types.py
metquest/guided_bfs.py
metquest/package_data.py
metquest/pathway_assembler.py
metquest.egg-info/PKG-INFO
metquest.egg-info/SOURCES.txt
metquest.egg-info/dependency_links.txt
metquest.egg-info/requires.txt
metquest.egg-info/top_level.txt
metquest/example/__init__.py
metquest/example/run_this_example.py
metquest/example/data/cutoff.txt
metquest/example/data/iJO1366.xml
metquest/example/data/iJO1366_.gpickle
metquest/example/data/iJO1366_namemap.pickle
metquest/example/data/seed_mets.txt
metquest/example/data/source_mets.txt
metquest/example/data/target_mets.txt